{
  "count": 639,
  "previous": null,
  "results": [
    {
      "url": "http://pokeapi.co/api/v2/move/1/",
      "name": "pound"
    },
    {
      "url": "http://pokeapi.co/api/v2/move/2/",
      "name": "karate-chop"
    },
    {
      "url": "http://pokeapi.co/api/v2/move/3/",
      "name": "double-slap"
    },
    {
      "url": "http://pokeapi.co/api/v2/move/4/",
      "name": "comet-punch"
    },
    {
      "url": "http://pokeapi.co/api/v2/move/5/",
      "name": "mega-punch"
    },
    {
      "url": "http://pokeapi.co/api/v2/move/6/",
      "name": "pay-day"
    },
    {
      "url": "http://pokeapi.co/api/v2/move/7/",
      "name": "fire-punch"
    },
    {
      "url": "http://pokeapi.co/api/v2/move/8/",
      "name": "ice-punch"
    },
    {
      "url": "http://pokeapi.co/api/v2/move/9/",
      "name": "thunder-punch"
    },
    {
      "url": "http://pokeapi.co/api/v2/move/10/",
      "name": "scratch"
    },
    {
      "url": "http://pokeapi.co/api/v2/move/11/",
      "name": "vice-grip"
    },
    {
      "url": "http://pokeapi.co/api/v2/move/12/",
      "name": "guillotine"
    },
    {
      "url": "http://pokeapi.co/api/v2/move/13/",
      "name": "razor-wind"
    },
    {
      "url": "http://pokeapi.co/api/v2/move/14/",
      "name": "swords-dance"
    },
    {
      "url": "http://pokeapi.co/api/v2/move/15/",
      "name": "cut"
    },
    {
      "url": "http://pokeapi.co/api/v2/move/16/",
      "name": "gust"
    },
    {
      "url": "http://pokeapi.co/api/v2/move/17/",
      "name": "wing-attack"
    },
    {
      "url": "http://pokeapi.co/api/v2/move/18/",
      "name": "whirlwind"
    },
    {
      "url": "http://pokeapi.co/api/v2/move/19/",
      "name": "fly"
    },
    {
      "url": "http://pokeapi.co/api/v2/move/20/",
      "name": "bind"
    },
    {
      "url": "http://pokeapi.co/api/v2/move/21/",
      "name": "slam"
    },
    {
      "url": "http://pokeapi.co/api/v2/move/22/",
      "name": "vine-whip"
    },
    {
      "url": "http://pokeapi.co/api/v2/move/23/",
      "name": "stomp"
    },
    {
      "url": "http://pokeapi.co/api/v2/move/24/",
      "name": "double-kick"
    },
    {
      "url": "http://pokeapi.co/api/v2/move/25/",
      "name": "mega-kick"
    },
    {
      "url": "http://pokeapi.co/api/v2/move/26/",
      "name": "jump-kick"
    },
    {
      "url": "http://pokeapi.co/api/v2/move/27/",
      "name": "rolling-kick"
    },
    {
      "url": "http://pokeapi.co/api/v2/move/28/",
      "name": "sand-attack"
    },
    {
      "url": "http://pokeapi.co/api/v2/move/29/",
      "name": "headbutt"
    },
    {
      "url": "http://pokeapi.co/api/v2/move/30/",
      "name": "horn-attack"
    },
    {
      "url": "http://pokeapi.co/api/v2/move/31/",
      "name": "fury-attack"
    },
    {
      "url": "http://pokeapi.co/api/v2/move/32/",
      "name": "horn-drill"
    },
    {
      "url": "http://pokeapi.co/api/v2/move/33/",
      "name": "tackle"
    },
    {
      "url": "http://pokeapi.co/api/v2/move/34/",
      "name": "body-slam"
    },
    {
      "url": "http://pokeapi.co/api/v2/move/35/",
      "name": "wrap"
    },
    {
      "url": "http://pokeapi.co/api/v2/move/36/",
      "name": "take-down"
    },
    {
      "url": "http://pokeapi.co/api/v2/move/37/",
      "name": "thrash"
    },
    {
      "url": "http://pokeapi.co/api/v2/move/38/",
      "name": "double-edge"
    },
    {
      "url": "http://pokeapi.co/api/v2/move/39/",
      "name": "tail-whip"
    },
    {
      "url": "http://pokeapi.co/api/v2/move/40/",
      "name": "poison-sting"
    },
    {
      "url": "http://pokeapi.co/api/v2/move/41/",
      "name": "twineedle"
    },
    {
      "url": "http://pokeapi.co/api/v2/move/42/",
      "name": "pin-missile"
    },
    {
      "url": "http://pokeapi.co/api/v2/move/43/",
      "name": "leer"
    },
    {
      "url": "http://pokeapi.co/api/v2/move/44/",
      "name": "bite"
    },
    {
      "url": "http://pokeapi.co/api/v2/move/45/",
      "name": "growl"
    },
    {
      "url": "http://pokeapi.co/api/v2/move/46/",
      "name": "roar"
    },
    {
      "url": "http://pokeapi.co/api/v2/move/47/",
      "name": "sing"
    },
    {
      "url": "http://pokeapi.co/api/v2/move/48/",
      "name": "supersonic"
    },
    {
      "url": "http://pokeapi.co/api/v2/move/49/",
      "name": "sonic-boom"
    },
    {
      "url": "http://pokeapi.co/api/v2/move/50/",
      "name": "disable"
    },
    {
      "url": "http://pokeapi.co/api/v2/move/51/",
      "name": "acid"
    },
    {
      "url": "http://pokeapi.co/api/v2/move/52/",
      "name": "ember"
    },
    {
      "url": "http://pokeapi.co/api/v2/move/53/",
      "name": "flamethrower"
    },
    {
      "url": "http://pokeapi.co/api/v2/move/54/",
      "name": "mist"
    },
    {
      "url": "http://pokeapi.co/api/v2/move/55/",
      "name": "water-gun"
    },
    {
      "url": "http://pokeapi.co/api/v2/move/56/",
      "name": "hydro-pump"
    },
    {
      "url": "http://pokeapi.co/api/v2/move/57/",
      "name": "surf"
    },
    {
      "url": "http://pokeapi.co/api/v2/move/58/",
      "name": "ice-beam"
    },
    {
      "url": "http://pokeapi.co/api/v2/move/59/",
      "name": "blizzard"
    },
    {
      "url": "http://pokeapi.co/api/v2/move/60/",
      "name": "psybeam"
    },
    {
      "url": "http://pokeapi.co/api/v2/move/61/",
      "name": "bubble-beam"
    },
    {
      "url": "http://pokeapi.co/api/v2/move/62/",
      "name": "aurora-beam"
    },
    {
      "url": "http://pokeapi.co/api/v2/move/63/",
      "name": "hyper-beam"
    },
    {
      "url": "http://pokeapi.co/api/v2/move/64/",
      "name": "peck"
    },
    {
      "url": "http://pokeapi.co/api/v2/move/65/",
      "name": "drill-peck"
    },
    {
      "url": "http://pokeapi.co/api/v2/move/66/",
      "name": "submission"
    },
    {
      "url": "http://pokeapi.co/api/v2/move/67/",
      "name": "low-kick"
    },
    {
      "url": "http://pokeapi.co/api/v2/move/68/",
      "name": "counter"
    },
    {
      "url": "http://pokeapi.co/api/v2/move/69/",
      "name": "seismic-toss"
    },
    {
      "url": "http://pokeapi.co/api/v2/move/70/",
      "name": "strength"
    },
    {
      "url": "http://pokeapi.co/api/v2/move/71/",
      "name": "absorb"
    },
    {
      "url": "http://pokeapi.co/api/v2/move/72/",
      "name": "mega-drain"
    },
    {
      "url": "http://pokeapi.co/api/v2/move/73/",
      "name": "leech-seed"
    },
    {
      "url": "http://pokeapi.co/api/v2/move/74/",
      "name": "growth"
    },
    {
      "url": "http://pokeapi.co/api/v2/move/75/",
      "name": "razor-leaf"
    },
    {
      "url": "http://pokeapi.co/api/v2/move/76/",
      "name": "solar-beam"
    },
    {
      "url": "http://pokeapi.co/api/v2/move/77/",
      "name": "poison-powder"
    },
    {
      "url": "http://pokeapi.co/api/v2/move/78/",
      "name": "stun-spore"
    },
    {
      "url": "http://pokeapi.co/api/v2/move/79/",
      "name": "sleep-powder"
    },
    {
      "url": "http://pokeapi.co/api/v2/move/80/",
      "name": "petal-dance"
    },
    {
      "url": "http://pokeapi.co/api/v2/move/81/",
      "name": "string-shot"
    },
    {
      "url": "http://pokeapi.co/api/v2/move/82/",
      "name": "dragon-rage"
    },
    {
      "url": "http://pokeapi.co/api/v2/move/83/",
      "name": "fire-spin"
    },
    {
      "url": "http://pokeapi.co/api/v2/move/84/",
      "name": "thunder-shock"
    },
    {
      "url": "http://pokeapi.co/api/v2/move/85/",
      "name": "thunderbolt"
    },
    {
      "url": "http://pokeapi.co/api/v2/move/86/",
      "name": "thunder-wave"
    },
    {
      "url": "http://pokeapi.co/api/v2/move/87/",
      "name": "thunder"
    },
    {
      "url": "http://pokeapi.co/api/v2/move/88/",
      "name": "rock-throw"
    },
    {
      "url": "http://pokeapi.co/api/v2/move/89/",
      "name": "earthquake"
    },
    {
      "url": "http://pokeapi.co/api/v2/move/90/",
      "name": "fissure"
    },
    {
      "url": "http://pokeapi.co/api/v2/move/91/",
      "name": "dig"
    },
    {
      "url": "http://pokeapi.co/api/v2/move/92/",
      "name": "toxic"
    },
    {
      "url": "http://pokeapi.co/api/v2/move/93/",
      "name": "confusion"
    },
    {
      "url": "http://pokeapi.co/api/v2/move/94/",
      "name": "psychic"
    },
    {
      "url": "http://pokeapi.co/api/v2/move/95/",
      "name": "hypnosis"
    },
    {
      "url": "http://pokeapi.co/api/v2/move/96/",
      "name": "meditate"
    },
    {
      "url": "http://pokeapi.co/api/v2/move/97/",
      "name": "agility"
    },
    {
      "url": "http://pokeapi.co/api/v2/move/98/",
      "name": "quick-attack"
    },
    {
      "url": "http://pokeapi.co/api/v2/move/99/",
      "name": "rage"
    },
    {
      "url": "http://pokeapi.co/api/v2/move/100/",
      "name": "teleport"
    },
    {
      "url": "http://pokeapi.co/api/v2/move/101/",
      "name": "night-shade"
    },
    {
      "url": "http://pokeapi.co/api/v2/move/102/",
      "name": "mimic"
    },
    {
      "url": "http://pokeapi.co/api/v2/move/103/",
      "name": "screech"
    },
    {
      "url": "http://pokeapi.co/api/v2/move/104/",
      "name": "double-team"
    },
    {
      "url": "http://pokeapi.co/api/v2/move/105/",
      "name": "recover"
    },
    {
      "url": "http://pokeapi.co/api/v2/move/106/",
      "name": "harden"
    },
    {
      "url": "http://pokeapi.co/api/v2/move/107/",
      "name": "minimize"
    },
    {
      "url": "http://pokeapi.co/api/v2/move/108/",
      "name": "smokescreen"
    },
    {
      "url": "http://pokeapi.co/api/v2/move/109/",
      "name": "confuse-ray"
    },
    {
      "url": "http://pokeapi.co/api/v2/move/110/",
      "name": "withdraw"
    },
    {
      "url": "http://pokeapi.co/api/v2/move/111/",
      "name": "defense-curl"
    },
    {
      "url": "http://pokeapi.co/api/v2/move/112/",
      "name": "barrier"
    },
    {
      "url": "http://pokeapi.co/api/v2/move/113/",
      "name": "light-screen"
    },
    {
      "url": "http://pokeapi.co/api/v2/move/114/",
      "name": "haze"
    },
    {
      "url": "http://pokeapi.co/api/v2/move/115/",
      "name": "reflect"
    },
    {
      "url": "http://pokeapi.co/api/v2/move/116/",
      "name": "focus-energy"
    },
    {
      "url": "http://pokeapi.co/api/v2/move/117/",
      "name": "bide"
    },
    {
      "url": "http://pokeapi.co/api/v2/move/118/",
      "name": "metronome"
    },
    {
      "url": "http://pokeapi.co/api/v2/move/119/",
      "name": "mirror-move"
    },
    {
      "url": "http://pokeapi.co/api/v2/move/120/",
      "name": "self-destruct"
    },
    {
      "url": "http://pokeapi.co/api/v2/move/121/",
      "name": "egg-bomb"
    },
    {
      "url": "http://pokeapi.co/api/v2/move/122/",
      "name": "lick"
    },
    {
      "url": "http://pokeapi.co/api/v2/move/123/",
      "name": "smog"
    },
    {
      "url": "http://pokeapi.co/api/v2/move/124/",
      "name": "sludge"
    },
    {
      "url": "http://pokeapi.co/api/v2/move/125/",
      "name": "bone-club"
    },
    {
      "url": "http://pokeapi.co/api/v2/move/126/",
      "name": "fire-blast"
    },
    {
      "url": "http://pokeapi.co/api/v2/move/127/",
      "name": "waterfall"
    },
    {
      "url": "http://pokeapi.co/api/v2/move/128/",
      "name": "clamp"
    },
    {
      "url": "http://pokeapi.co/api/v2/move/129/",
      "name": "swift"
    },
    {
      "url": "http://pokeapi.co/api/v2/move/130/",
      "name": "skull-bash"
    },
    {
      "url": "http://pokeapi.co/api/v2/move/131/",
      "name": "spike-cannon"
    },
    {
      "url": "http://pokeapi.co/api/v2/move/132/",
      "name": "constrict"
    },
    {
      "url": "http://pokeapi.co/api/v2/move/133/",
      "name": "amnesia"
    },
    {
      "url": "http://pokeapi.co/api/v2/move/134/",
      "name": "kinesis"
    },
    {
      "url": "http://pokeapi.co/api/v2/move/135/",
      "name": "soft-boiled"
    },
    {
      "url": "http://pokeapi.co/api/v2/move/136/",
      "name": "high-jump-kick"
    },
    {
      "url": "http://pokeapi.co/api/v2/move/137/",
      "name": "glare"
    },
    {
      "url": "http://pokeapi.co/api/v2/move/138/",
      "name": "dream-eater"
    },
    {
      "url": "http://pokeapi.co/api/v2/move/139/",
      "name": "poison-gas"
    },
    {
      "url": "http://pokeapi.co/api/v2/move/140/",
      "name": "barrage"
    },
    {
      "url": "http://pokeapi.co/api/v2/move/141/",
      "name": "leech-life"
    },
    {
      "url": "http://pokeapi.co/api/v2/move/142/",
      "name": "lovely-kiss"
    },
    {
      "url": "http://pokeapi.co/api/v2/move/143/",
      "name": "sky-attack"
    },
    {
      "url": "http://pokeapi.co/api/v2/move/144/",
      "name": "transform"
    },
    {
      "url": "http://pokeapi.co/api/v2/move/145/",
      "name": "bubble"
    },
    {
      "url": "http://pokeapi.co/api/v2/move/146/",
      "name": "dizzy-punch"
    },
    {
      "url": "http://pokeapi.co/api/v2/move/147/",
      "name": "spore"
    },
    {
      "url": "http://pokeapi.co/api/v2/move/148/",
      "name": "flash"
    },
    {
      "url": "http://pokeapi.co/api/v2/move/149/",
      "name": "psywave"
    },
    {
      "url": "http://pokeapi.co/api/v2/move/150/",
      "name": "splash"
    },
    {
      "url": "http://pokeapi.co/api/v2/move/151/",
      "name": "acid-armor"
    },
    {
      "url": "http://pokeapi.co/api/v2/move/152/",
      "name": "crabhammer"
    },
    {
      "url": "http://pokeapi.co/api/v2/move/153/",
      "name": "explosion"
    },
    {
      "url": "http://pokeapi.co/api/v2/move/154/",
      "name": "fury-swipes"
    },
    {
      "url": "http://pokeapi.co/api/v2/move/155/",
      "name": "bonemerang"
    },
    {
      "url": "http://pokeapi.co/api/v2/move/156/",
      "name": "rest"
    },
    {
      "url": "http://pokeapi.co/api/v2/move/157/",
      "name": "rock-slide"
    },
    {
      "url": "http://pokeapi.co/api/v2/move/158/",
      "name": "hyper-fang"
    },
    {
      "url": "http://pokeapi.co/api/v2/move/159/",
      "name": "sharpen"
    },
    {
      "url": "http://pokeapi.co/api/v2/move/160/",
      "name": "conversion"
    },
    {
      "url": "http://pokeapi.co/api/v2/move/161/",
      "name": "tri-attack"
    },
    {
      "url": "http://pokeapi.co/api/v2/move/162/",
      "name": "super-fang"
    },
    {
      "url": "http://pokeapi.co/api/v2/move/163/",
      "name": "slash"
    },
    {
      "url": "http://pokeapi.co/api/v2/move/164/",
      "name": "substitute"
    },
    {
      "url": "http://pokeapi.co/api/v2/move/165/",
      "name": "struggle"
    },
    {
      "url": "http://pokeapi.co/api/v2/move/166/",
      "name": "sketch"
    },
    {
      "url": "http://pokeapi.co/api/v2/move/167/",
      "name": "triple-kick"
    },
    {
      "url": "http://pokeapi.co/api/v2/move/168/",
      "name": "thief"
    },
    {
      "url": "http://pokeapi.co/api/v2/move/169/",
      "name": "spider-web"
    },
    {
      "url": "http://pokeapi.co/api/v2/move/170/",
      "name": "mind-reader"
    },
    {
      "url": "http://pokeapi.co/api/v2/move/171/",
      "name": "nightmare"
    },
    {
      "url": "http://pokeapi.co/api/v2/move/172/",
      "name": "flame-wheel"
    },
    {
      "url": "http://pokeapi.co/api/v2/move/173/",
      "name": "snore"
    },
    {
      "url": "http://pokeapi.co/api/v2/move/174/",
      "name": "curse"
    },
    {
      "url": "http://pokeapi.co/api/v2/move/175/",
      "name": "flail"
    },
    {
      "url": "http://pokeapi.co/api/v2/move/176/",
      "name": "conversion-2"
    },
    {
      "url": "http://pokeapi.co/api/v2/move/177/",
      "name": "aeroblast"
    },
    {
      "url": "http://pokeapi.co/api/v2/move/178/",
      "name": "cotton-spore"
    },
    {
      "url": "http://pokeapi.co/api/v2/move/179/",
      "name": "reversal"
    },
    {
      "url": "http://pokeapi.co/api/v2/move/180/",
      "name": "spite"
    },
    {
      "url": "http://pokeapi.co/api/v2/move/181/",
      "name": "powder-snow"
    },
    {
      "url": "http://pokeapi.co/api/v2/move/182/",
      "name": "protect"
    },
    {
      "url": "http://pokeapi.co/api/v2/move/183/",
      "name": "mach-punch"
    },
    {
      "url": "http://pokeapi.co/api/v2/move/184/",
      "name": "scary-face"
    },
    {
      "url": "http://pokeapi.co/api/v2/move/185/",
      "name": "feint-attack"
    },
    {
      "url": "http://pokeapi.co/api/v2/move/186/",
      "name": "sweet-kiss"
    },
    {
      "url": "http://pokeapi.co/api/v2/move/187/",
      "name": "belly-drum"
    },
    {
      "url": "http://pokeapi.co/api/v2/move/188/",
      "name": "sludge-bomb"
    },
    {
      "url": "http://pokeapi.co/api/v2/move/189/",
      "name": "mud-slap"
    },
    {
      "url": "http://pokeapi.co/api/v2/move/190/",
      "name": "octazooka"
    },
    {
      "url": "http://pokeapi.co/api/v2/move/191/",
      "name": "spikes"
    },
    {
      "url": "http://pokeapi.co/api/v2/move/192/",
      "name": "zap-cannon"
    },
    {
      "url": "http://pokeapi.co/api/v2/move/193/",
      "name": "foresight"
    },
    {
      "url": "http://pokeapi.co/api/v2/move/194/",
      "name": "destiny-bond"
    },
    {
      "url": "http://pokeapi.co/api/v2/move/195/",
      "name": "perish-song"
    },
    {
      "url": "http://pokeapi.co/api/v2/move/196/",
      "name": "icy-wind"
    },
    {
      "url": "http://pokeapi.co/api/v2/move/197/",
      "name": "detect"
    },
    {
      "url": "http://pokeapi.co/api/v2/move/198/",
      "name": "bone-rush"
    },
    {
      "url": "http://pokeapi.co/api/v2/move/199/",
      "name": "lock-on"
    },
    {
      "url": "http://pokeapi.co/api/v2/move/200/",
      "name": "outrage"
    },
    {
      "url": "http://pokeapi.co/api/v2/move/201/",
      "name": "sandstorm"
    },
    {
      "url": "http://pokeapi.co/api/v2/move/202/",
      "name": "giga-drain"
    },
    {
      "url": "http://pokeapi.co/api/v2/move/203/",
      "name": "endure"
    },
    {
      "url": "http://pokeapi.co/api/v2/move/204/",
      "name": "charm"
    },
    {
      "url": "http://pokeapi.co/api/v2/move/205/",
      "name": "rollout"
    },
    {
      "url": "http://pokeapi.co/api/v2/move/206/",
      "name": "false-swipe"
    },
    {
      "url": "http://pokeapi.co/api/v2/move/207/",
      "name": "swagger"
    },
    {
      "url": "http://pokeapi.co/api/v2/move/208/",
      "name": "milk-drink"
    },
    {
      "url": "http://pokeapi.co/api/v2/move/209/",
      "name": "spark"
    },
    {
      "url": "http://pokeapi.co/api/v2/move/210/",
      "name": "fury-cutter"
    },
    {
      "url": "http://pokeapi.co/api/v2/move/211/",
      "name": "steel-wing"
    },
    {
      "url": "http://pokeapi.co/api/v2/move/212/",
      "name": "mean-look"
    },
    {
      "url": "http://pokeapi.co/api/v2/move/213/",
      "name": "attract"
    },
    {
      "url": "http://pokeapi.co/api/v2/move/214/",
      "name": "sleep-talk"
    },
    {
      "url": "http://pokeapi.co/api/v2/move/215/",
      "name": "heal-bell"
    },
    {
      "url": "http://pokeapi.co/api/v2/move/216/",
      "name": "return"
    },
    {
      "url": "http://pokeapi.co/api/v2/move/217/",
      "name": "present"
    },
    {
      "url": "http://pokeapi.co/api/v2/move/218/",
      "name": "frustration"
    },
    {
      "url": "http://pokeapi.co/api/v2/move/219/",
      "name": "safeguard"
    },
    {
      "url": "http://pokeapi.co/api/v2/move/220/",
      "name": "pain-split"
    },
    {
      "url": "http://pokeapi.co/api/v2/move/221/",
      "name": "sacred-fire"
    },
    {
      "url": "http://pokeapi.co/api/v2/move/222/",
      "name": "magnitude"
    },
    {
      "url": "http://pokeapi.co/api/v2/move/223/",
      "name": "dynamic-punch"
    },
    {
      "url": "http://pokeapi.co/api/v2/move/224/",
      "name": "megahorn"
    },
    {
      "url": "http://pokeapi.co/api/v2/move/225/",
      "name": "dragon-breath"
    },
    {
      "url": "http://pokeapi.co/api/v2/move/226/",
      "name": "baton-pass"
    },
    {
      "url": "http://pokeapi.co/api/v2/move/227/",
      "name": "encore"
    },
    {
      "url": "http://pokeapi.co/api/v2/move/228/",
      "name": "pursuit"
    },
    {
      "url": "http://pokeapi.co/api/v2/move/229/",
      "name": "rapid-spin"
    },
    {
      "url": "http://pokeapi.co/api/v2/move/230/",
      "name": "sweet-scent"
    },
    {
      "url": "http://pokeapi.co/api/v2/move/231/",
      "name": "iron-tail"
    },
    {
      "url": "http://pokeapi.co/api/v2/move/232/",
      "name": "metal-claw"
    },
    {
      "url": "http://pokeapi.co/api/v2/move/233/",
      "name": "vital-throw"
    },
    {
      "url": "http://pokeapi.co/api/v2/move/234/",
      "name": "morning-sun"
    },
    {
      "url": "http://pokeapi.co/api/v2/move/235/",
      "name": "synthesis"
    },
    {
      "url": "http://pokeapi.co/api/v2/move/236/",
      "name": "moonlight"
    },
    {
      "url": "http://pokeapi.co/api/v2/move/237/",
      "name": "hidden-power"
    },
    {
      "url": "http://pokeapi.co/api/v2/move/238/",
      "name": "cross-chop"
    },
    {
      "url": "http://pokeapi.co/api/v2/move/239/",
      "name": "twister"
    },
    {
      "url": "http://pokeapi.co/api/v2/move/240/",
      "name": "rain-dance"
    },
    {
      "url": "http://pokeapi.co/api/v2/move/241/",
      "name": "sunny-day"
    },
    {
      "url": "http://pokeapi.co/api/v2/move/242/",
      "name": "crunch"
    },
    {
      "url": "http://pokeapi.co/api/v2/move/243/",
      "name": "mirror-coat"
    },
    {
      "url": "http://pokeapi.co/api/v2/move/244/",
      "name": "psych-up"
    },
    {
      "url": "http://pokeapi.co/api/v2/move/245/",
      "name": "extreme-speed"
    },
    {
      "url": "http://pokeapi.co/api/v2/move/246/",
      "name": "ancient-power"
    },
    {
      "url": "http://pokeapi.co/api/v2/move/247/",
      "name": "shadow-ball"
    },
    {
      "url": "http://pokeapi.co/api/v2/move/248/",
      "name": "future-sight"
    },
    {
      "url": "http://pokeapi.co/api/v2/move/249/",
      "name": "rock-smash"
    },
    {
      "url": "http://pokeapi.co/api/v2/move/250/",
      "name": "whirlpool"
    },
    {
      "url": "http://pokeapi.co/api/v2/move/251/",
      "name": "beat-up"
    },
    {
      "url": "http://pokeapi.co/api/v2/move/252/",
      "name": "fake-out"
    },
    {
      "url": "http://pokeapi.co/api/v2/move/253/",
      "name": "uproar"
    },
    {
      "url": "http://pokeapi.co/api/v2/move/254/",
      "name": "stockpile"
    },
    {
      "url": "http://pokeapi.co/api/v2/move/255/",
      "name": "spit-up"
    },
    {
      "url": "http://pokeapi.co/api/v2/move/256/",
      "name": "swallow"
    },
    {
      "url": "http://pokeapi.co/api/v2/move/257/",
      "name": "heat-wave"
    },
    {
      "url": "http://pokeapi.co/api/v2/move/258/",
      "name": "hail"
    },
    {
      "url": "http://pokeapi.co/api/v2/move/259/",
      "name": "torment"
    },
    {
      "url": "http://pokeapi.co/api/v2/move/260/",
      "name": "flatter"
    },
    {
      "url": "http://pokeapi.co/api/v2/move/261/",
      "name": "will-o-wisp"
    },
    {
      "url": "http://pokeapi.co/api/v2/move/262/",
      "name": "memento"
    },
    {
      "url": "http://pokeapi.co/api/v2/move/263/",
      "name": "facade"
    },
    {
      "url": "http://pokeapi.co/api/v2/move/264/",
      "name": "focus-punch"
    },
    {
      "url": "http://pokeapi.co/api/v2/move/265/",
      "name": "smelling-salts"
    },
    {
      "url": "http://pokeapi.co/api/v2/move/266/",
      "name": "follow-me"
    },
    {
      "url": "http://pokeapi.co/api/v2/move/267/",
      "name": "nature-power"
    },
    {
      "url": "http://pokeapi.co/api/v2/move/268/",
      "name": "charge"
    },
    {
      "url": "http://pokeapi.co/api/v2/move/269/",
      "name": "taunt"
    },
    {
      "url": "http://pokeapi.co/api/v2/move/270/",
      "name": "helping-hand"
    },
    {
      "url": "http://pokeapi.co/api/v2/move/271/",
      "name": "trick"
    },
    {
      "url": "http://pokeapi.co/api/v2/move/272/",
      "name": "role-play"
    },
    {
      "url": "http://pokeapi.co/api/v2/move/273/",
      "name": "wish"
    },
    {
      "url": "http://pokeapi.co/api/v2/move/274/",
      "name": "assist"
    },
    {
      "url": "http://pokeapi.co/api/v2/move/275/",
      "name": "ingrain"
    },
    {
      "url": "http://pokeapi.co/api/v2/move/276/",
      "name": "superpower"
    },
    {
      "url": "http://pokeapi.co/api/v2/move/277/",
      "name": "magic-coat"
    },
    {
      "url": "http://pokeapi.co/api/v2/move/278/",
      "name": "recycle"
    },
    {
      "url": "http://pokeapi.co/api/v2/move/279/",
      "name": "revenge"
    },
    {
      "url": "http://pokeapi.co/api/v2/move/280/",
      "name": "brick-break"
    },
    {
      "url": "http://pokeapi.co/api/v2/move/281/",
      "name": "yawn"
    },
    {
      "url": "http://pokeapi.co/api/v2/move/282/",
      "name": "knock-off"
    },
    {
      "url": "http://pokeapi.co/api/v2/move/283/",
      "name": "endeavor"
    },
    {
      "url": "http://pokeapi.co/api/v2/move/284/",
      "name": "eruption"
    },
    {
      "url": "http://pokeapi.co/api/v2/move/285/",
      "name": "skill-swap"
    },
    {
      "url": "http://pokeapi.co/api/v2/move/286/",
      "name": "imprison"
    },
    {
      "url": "http://pokeapi.co/api/v2/move/287/",
      "name": "refresh"
    },
    {
      "url": "http://pokeapi.co/api/v2/move/288/",
      "name": "grudge"
    },
    {
      "url": "http://pokeapi.co/api/v2/move/289/",
      "name": "snatch"
    },
    {
      "url": "http://pokeapi.co/api/v2/move/290/",
      "name": "secret-power"
    },
    {
      "url": "http://pokeapi.co/api/v2/move/291/",
      "name": "dive"
    },
    {
      "url": "http://pokeapi.co/api/v2/move/292/",
      "name": "arm-thrust"
    },
    {
      "url": "http://pokeapi.co/api/v2/move/293/",
      "name": "camouflage"
    },
    {
      "url": "http://pokeapi.co/api/v2/move/294/",
      "name": "tail-glow"
    },
    {
      "url": "http://pokeapi.co/api/v2/move/295/",
      "name": "luster-purge"
    },
    {
      "url": "http://pokeapi.co/api/v2/move/296/",
      "name": "mist-ball"
    },
    {
      "url": "http://pokeapi.co/api/v2/move/297/",
      "name": "feather-dance"
    },
    {
      "url": "http://pokeapi.co/api/v2/move/298/",
      "name": "teeter-dance"
    },
    {
      "url": "http://pokeapi.co/api/v2/move/299/",
      "name": "blaze-kick"
    },
    {
      "url": "http://pokeapi.co/api/v2/move/300/",
      "name": "mud-sport"
    },
    {
      "url": "http://pokeapi.co/api/v2/move/301/",
      "name": "ice-ball"
    },
    {
      "url": "http://pokeapi.co/api/v2/move/302/",
      "name": "needle-arm"
    },
    {
      "url": "http://pokeapi.co/api/v2/move/303/",
      "name": "slack-off"
    },
    {
      "url": "http://pokeapi.co/api/v2/move/304/",
      "name": "hyper-voice"
    },
    {
      "url": "http://pokeapi.co/api/v2/move/305/",
      "name": "poison-fang"
    },
    {
      "url": "http://pokeapi.co/api/v2/move/306/",
      "name": "crush-claw"
    },
    {
      "url": "http://pokeapi.co/api/v2/move/307/",
      "name": "blast-burn"
    },
    {
      "url": "http://pokeapi.co/api/v2/move/308/",
      "name": "hydro-cannon"
    },
    {
      "url": "http://pokeapi.co/api/v2/move/309/",
      "name": "meteor-mash"
    },
    {
      "url": "http://pokeapi.co/api/v2/move/310/",
      "name": "astonish"
    },
    {
      "url": "http://pokeapi.co/api/v2/move/311/",
      "name": "weather-ball"
    },
    {
      "url": "http://pokeapi.co/api/v2/move/312/",
      "name": "aromatherapy"
    },
    {
      "url": "http://pokeapi.co/api/v2/move/313/",
      "name": "fake-tears"
    },
    {
      "url": "http://pokeapi.co/api/v2/move/314/",
      "name": "air-cutter"
    },
    {
      "url": "http://pokeapi.co/api/v2/move/315/",
      "name": "overheat"
    },
    {
      "url": "http://pokeapi.co/api/v2/move/316/",
      "name": "odor-sleuth"
    },
    {
      "url": "http://pokeapi.co/api/v2/move/317/",
      "name": "rock-tomb"
    },
    {
      "url": "http://pokeapi.co/api/v2/move/318/",
      "name": "silver-wind"
    },
    {
      "url": "http://pokeapi.co/api/v2/move/319/",
      "name": "metal-sound"
    },
    {
      "url": "http://pokeapi.co/api/v2/move/320/",
      "name": "grass-whistle"
    },
    {
      "url": "http://pokeapi.co/api/v2/pokemon/321/",
      "name": "wailord"
    },
    {
      "url": "http://pokeapi.co/api/v2/pokemon/322/",
      "name": "numel"
    },
    {
      "url": "http://pokeapi.co/api/v2/pokemon/323/",
      "name": "camerupt"
    },
    {
      "url": "http://pokeapi.co/api/v2/pokemon/324/",
      "name": "torkoal"
    },
    {
      "url": "http://pokeapi.co/api/v2/pokemon/325/",
      "name": "spoink"
    },
    {
      "url": "http://pokeapi.co/api/v2/pokemon/326/",
      "name": "grumpig"
    },
    {
      "url": "http://pokeapi.co/api/v2/pokemon/327/",
      "name": "spinda"
    },
    {
      "url": "http://pokeapi.co/api/v2/pokemon/328/",
      "name": "trapinch"
    },
    {
      "url": "http://pokeapi.co/api/v2/pokemon/329/",
      "name": "vibrava"
    },
    {
      "url": "http://pokeapi.co/api/v2/pokemon/330/",
      "name": "flygon"
    },
    {
      "url": "http://pokeapi.co/api/v2/pokemon/331/",
      "name": "cacnea"
    },
    {
      "url": "http://pokeapi.co/api/v2/pokemon/332/",
      "name": "cacturne"
    },
    {
      "url": "http://pokeapi.co/api/v2/pokemon/333/",
      "name": "swablu"
    },
    {
      "url": "http://pokeapi.co/api/v2/pokemon/334/",
      "name": "altaria"
    },
    {
      "url": "http://pokeapi.co/api/v2/pokemon/335/",
      "name": "zangoose"
    },
    {
      "url": "http://pokeapi.co/api/v2/pokemon/336/",
      "name": "seviper"
    },
    {
      "url": "http://pokeapi.co/api/v2/pokemon/337/",
      "name": "lunatone"
    },
    {
      "url": "http://pokeapi.co/api/v2/pokemon/338/",
      "name": "solrock"
    },
    {
      "url": "http://pokeapi.co/api/v2/pokemon/339/",
      "name": "barboach"
    },
    {
      "url": "http://pokeapi.co/api/v2/pokemon/340/",
      "name": "whiscash"
    },
    {
      "url": "http://pokeapi.co/api/v2/pokemon/341/",
      "name": "corphish"
    },
    {
      "url": "http://pokeapi.co/api/v2/pokemon/342/",
      "name": "crawdaunt"
    },
    {
      "url": "http://pokeapi.co/api/v2/pokemon/343/",
      "name": "baltoy"
    },
    {
      "url": "http://pokeapi.co/api/v2/pokemon/344/",
      "name": "claydol"
    },
    {
      "url": "http://pokeapi.co/api/v2/pokemon/345/",
      "name": "lileep"
    },
    {
      "url": "http://pokeapi.co/api/v2/pokemon/346/",
      "name": "cradily"
    },
    {
      "url": "http://pokeapi.co/api/v2/pokemon/347/",
      "name": "anorith"
    },
    {
      "url": "http://pokeapi.co/api/v2/pokemon/348/",
      "name": "armaldo"
    },
    {
      "url": "http://pokeapi.co/api/v2/pokemon/349/",
      "name": "feebas"
    },
    {
      "url": "http://pokeapi.co/api/v2/pokemon/350/",
      "name": "milotic"
    },
    {
      "url": "http://pokeapi.co/api/v2/pokemon/351/",
      "name": "castform"
    },
    {
      "url": "http://pokeapi.co/api/v2/pokemon/352/",
      "name": "kecleon"
    },
    {
      "url": "http://pokeapi.co/api/v2/pokemon/353/",
      "name": "shuppet"
    },
    {
      "url": "http://pokeapi.co/api/v2/pokemon/354/",
      "name": "banette"
    },
    {
      "url": "http://pokeapi.co/api/v2/pokemon/355/",
      "name": "duskull"
    },
    {
      "url": "http://pokeapi.co/api/v2/pokemon/356/",
      "name": "dusclops"
    },
    {
      "url": "http://pokeapi.co/api/v2/pokemon/357/",
      "name": "tropius"
    },
    {
      "url": "http://pokeapi.co/api/v2/pokemon/358/",
      "name": "chimecho"
    },
    {
      "url": "http://pokeapi.co/api/v2/pokemon/359/",
      "name": "absol"
    },
    {
      "url": "http://pokeapi.co/api/v2/pokemon/360/",
      "name": "wynaut"
    },
    {
      "url": "http://pokeapi.co/api/v2/pokemon/361/",
      "name": "snorunt"
    },
    {
      "url": "http://pokeapi.co/api/v2/pokemon/362/",
      "name": "glalie"
    },
    {
      "url": "http://pokeapi.co/api/v2/pokemon/363/",
      "name": "spheal"
    },
    {
      "url": "http://pokeapi.co/api/v2/pokemon/364/",
      "name": "sealeo"
    },
    {
      "url": "http://pokeapi.co/api/v2/pokemon/365/",
      "name": "walrein"
    },
    {
      "url": "http://pokeapi.co/api/v2/pokemon/366/",
      "name": "clamperl"
    },
    {
      "url": "http://pokeapi.co/api/v2/pokemon/367/",
      "name": "huntail"
    },
    {
      "url": "http://pokeapi.co/api/v2/pokemon/368/",
      "name": "gorebyss"
    },
    {
      "url": "http://pokeapi.co/api/v2/pokemon/369/",
      "name": "relicanth"
    },
    {
      "url": "http://pokeapi.co/api/v2/pokemon/370/",
      "name": "luvdisc"
    },
    {
      "url": "http://pokeapi.co/api/v2/pokemon/371/",
      "name": "bagon"
    },
    {
      "url": "http://pokeapi.co/api/v2/pokemon/372/",
      "name": "shelgon"
    },
    {
      "url": "http://pokeapi.co/api/v2/pokemon/373/",
      "name": "salamence"
    },
    {
      "url": "http://pokeapi.co/api/v2/pokemon/374/",
      "name": "beldum"
    },
    {
      "url": "http://pokeapi.co/api/v2/pokemon/375/",
      "name": "metang"
    },
    {
      "url": "http://pokeapi.co/api/v2/pokemon/376/",
      "name": "metagross"
    },
    {
      "url": "http://pokeapi.co/api/v2/pokemon/377/",
      "name": "regirock"
    },
    {
      "url": "http://pokeapi.co/api/v2/pokemon/378/",
      "name": "regice"
    },
    {
      "url": "http://pokeapi.co/api/v2/pokemon/379/",
      "name": "registeel"
    },
    {
      "url": "http://pokeapi.co/api/v2/pokemon/380/",
      "name": "latias"
    },
    {
      "url": "http://pokeapi.co/api/v2/pokemon/381/",
      "name": "latios"
    },
    {
      "url": "http://pokeapi.co/api/v2/pokemon/382/",
      "name": "kyogre"
    },
    {
      "url": "http://pokeapi.co/api/v2/pokemon/383/",
      "name": "groudon"
    },
    {
      "url": "http://pokeapi.co/api/v2/pokemon/384/",
      "name": "rayquaza"
    },
    {
      "url": "http://pokeapi.co/api/v2/pokemon/385/",
      "name": "jirachi"
    },
    {
      "url": "http://pokeapi.co/api/v2/pokemon/386/",
      "name": "deoxys-normal"
    },
    {
      "url": "http://pokeapi.co/api/v2/pokemon/387/",
      "name": "turtwig"
    },
    {
      "url": "http://pokeapi.co/api/v2/pokemon/388/",
      "name": "grotle"
    },
    {
      "url": "http://pokeapi.co/api/v2/pokemon/389/",
      "name": "torterra"
    },
    {
      "url": "http://pokeapi.co/api/v2/pokemon/390/",
      "name": "chimchar"
    },
    {
      "url": "http://pokeapi.co/api/v2/pokemon/391/",
      "name": "monferno"
    },
    {
      "url": "http://pokeapi.co/api/v2/pokemon/392/",
      "name": "infernape"
    },
    {
      "url": "http://pokeapi.co/api/v2/pokemon/393/",
      "name": "piplup"
    },
    {
      "url": "http://pokeapi.co/api/v2/pokemon/394/",
      "name": "prinplup"
    },
    {
      "url": "http://pokeapi.co/api/v2/pokemon/395/",
      "name": "empoleon"
    },
    {
      "url": "http://pokeapi.co/api/v2/pokemon/396/",
      "name": "starly"
    },
    {
      "url": "http://pokeapi.co/api/v2/pokemon/397/",
      "name": "staravia"
    },
    {
      "url": "http://pokeapi.co/api/v2/pokemon/398/",
      "name": "staraptor"
    },
    {
      "url": "http://pokeapi.co/api/v2/pokemon/399/",
      "name": "bidoof"
    },
    {
      "url": "http://pokeapi.co/api/v2/pokemon/400/",
      "name": "bibarel"
    },
    {
      "url": "http://pokeapi.co/api/v2/pokemon/401/",
      "name": "kricketot"
    },
    {
      "url": "http://pokeapi.co/api/v2/pokemon/402/",
      "name": "kricketune"
    },
    {
      "url": "http://pokeapi.co/api/v2/pokemon/403/",
      "name": "shinx"
    },
    {
      "url": "http://pokeapi.co/api/v2/pokemon/404/",
      "name": "luxio"
    },
    {
      "url": "http://pokeapi.co/api/v2/pokemon/405/",
      "name": "luxray"
    },
    {
      "url": "http://pokeapi.co/api/v2/pokemon/406/",
      "name": "budew"
    },
    {
      "url": "http://pokeapi.co/api/v2/pokemon/407/",
      "name": "roserade"
    },
    {
      "url": "http://pokeapi.co/api/v2/pokemon/408/",
      "name": "cranidos"
    },
    {
      "url": "http://pokeapi.co/api/v2/pokemon/409/",
      "name": "rampardos"
    },
    {
      "url": "http://pokeapi.co/api/v2/pokemon/410/",
      "name": "shieldon"
    },
    {
      "url": "http://pokeapi.co/api/v2/pokemon/411/",
      "name": "bastiodon"
    },
    {
      "url": "http://pokeapi.co/api/v2/pokemon/412/",
      "name": "burmy"
    },
    {
      "url": "http://pokeapi.co/api/v2/pokemon/413/",
      "name": "wormadam-plant"
    },
    {
      "url": "http://pokeapi.co/api/v2/pokemon/414/",
      "name": "mothim"
    },
    {
      "url": "http://pokeapi.co/api/v2/pokemon/415/",
      "name": "combee"
    },
    {
      "url": "http://pokeapi.co/api/v2/pokemon/416/",
      "name": "vespiquen"
    },
    {
      "url": "http://pokeapi.co/api/v2/pokemon/417/",
      "name": "pachirisu"
    },
    {
      "url": "http://pokeapi.co/api/v2/pokemon/418/",
      "name": "buizel"
    },
    {
      "url": "http://pokeapi.co/api/v2/pokemon/419/",
      "name": "floatzel"
    },
    {
      "url": "http://pokeapi.co/api/v2/pokemon/420/",
      "name": "cherubi"
    },
    {
      "url": "http://pokeapi.co/api/v2/pokemon/421/",
      "name": "cherrim"
    },
    {
      "url": "http://pokeapi.co/api/v2/pokemon/422/",
      "name": "shellos"
    },
    {
      "url": "http://pokeapi.co/api/v2/pokemon/423/",
      "name": "gastrodon"
    },
    {
      "url": "http://pokeapi.co/api/v2/pokemon/424/",
      "name": "ambipom"
    },
    {
      "url": "http://pokeapi.co/api/v2/pokemon/425/",
      "name": "drifloon"
    },
    {
      "url": "http://pokeapi.co/api/v2/pokemon/426/",
      "name": "drifblim"
    },
    {
      "url": "http://pokeapi.co/api/v2/pokemon/427/",
      "name": "buneary"
    },
    {
      "url": "http://pokeapi.co/api/v2/pokemon/428/",
      "name": "lopunny"
    },
    {
      "url": "http://pokeapi.co/api/v2/pokemon/429/",
      "name": "mismagius"
    },
    {
      "url": "http://pokeapi.co/api/v2/pokemon/430/",
      "name": "honchkrow"
    },
    {
      "url": "http://pokeapi.co/api/v2/pokemon/431/",
      "name": "glameow"
    },
    {
      "url": "http://pokeapi.co/api/v2/pokemon/432/",
      "name": "purugly"
    },
    {
      "url": "http://pokeapi.co/api/v2/pokemon/433/",
      "name": "chingling"
    },
    {
      "url": "http://pokeapi.co/api/v2/pokemon/434/",
      "name": "stunky"
    },
    {
      "url": "http://pokeapi.co/api/v2/pokemon/435/",
      "name": "skuntank"
    },
    {
      "url": "http://pokeapi.co/api/v2/pokemon/436/",
      "name": "bronzor"
    },
    {
      "url": "http://pokeapi.co/api/v2/pokemon/437/",
      "name": "bronzong"
    },
    {
      "url": "http://pokeapi.co/api/v2/pokemon/438/",
      "name": "bonsly"
    },
    {
      "url": "http://pokeapi.co/api/v2/pokemon/439/",
      "name": "mime-jr"
    },
    {
      "url": "http://pokeapi.co/api/v2/pokemon/440/",
      "name": "happiny"
    },
    {
      "url": "http://pokeapi.co/api/v2/pokemon/441/",
      "name": "chatot"
    },
    {
      "url": "http://pokeapi.co/api/v2/pokemon/442/",
      "name": "spiritomb"
    },
    {
      "url": "http://pokeapi.co/api/v2/pokemon/443/",
      "name": "gible"
    },
    {
      "url": "http://pokeapi.co/api/v2/pokemon/444/",
      "name": "gabite"
    },
    {
      "url": "http://pokeapi.co/api/v2/pokemon/445/",
      "name": "garchomp"
    },
    {
      "url": "http://pokeapi.co/api/v2/pokemon/446/",
      "name": "munchlax"
    },
    {
      "url": "http://pokeapi.co/api/v2/pokemon/447/",
      "name": "riolu"
    },
    {
      "url": "http://pokeapi.co/api/v2/pokemon/448/",
      "name": "lucario"
    },
    {
      "url": "http://pokeapi.co/api/v2/pokemon/449/",
      "name": "hippopotas"
    },
    {
      "url": "http://pokeapi.co/api/v2/pokemon/450/",
      "name": "hippowdon"
    },
    {
      "url": "http://pokeapi.co/api/v2/pokemon/451/",
      "name": "skorupi"
    },
    {
      "url": "http://pokeapi.co/api/v2/pokemon/452/",
      "name": "drapion"
    },
    {
      "url": "http://pokeapi.co/api/v2/pokemon/453/",
      "name": "croagunk"
    },
    {
      "url": "http://pokeapi.co/api/v2/pokemon/454/",
      "name": "toxicroak"
    },
    {
      "url": "http://pokeapi.co/api/v2/pokemon/455/",
      "name": "carnivine"
    },
    {
      "url": "http://pokeapi.co/api/v2/pokemon/456/",
      "name": "finneon"
    },
    {
      "url": "http://pokeapi.co/api/v2/pokemon/457/",
      "name": "lumineon"
    },
    {
      "url": "http://pokeapi.co/api/v2/pokemon/458/",
      "name": "mantyke"
    },
    {
      "url": "http://pokeapi.co/api/v2/pokemon/459/",
      "name": "snover"
    },
    {
      "url": "http://pokeapi.co/api/v2/pokemon/460/",
      "name": "abomasnow"
    },
    {
      "url": "http://pokeapi.co/api/v2/pokemon/461/",
      "name": "weavile"
    },
    {
      "url": "http://pokeapi.co/api/v2/pokemon/462/",
      "name": "magnezone"
    },
    {
      "url": "http://pokeapi.co/api/v2/pokemon/463/",
      "name": "lickilicky"
    },
    {
      "url": "http://pokeapi.co/api/v2/pokemon/464/",
      "name": "rhyperior"
    },
    {
      "url": "http://pokeapi.co/api/v2/pokemon/465/",
      "name": "tangrowth"
    },
    {
      "url": "http://pokeapi.co/api/v2/pokemon/466/",
      "name": "electivire"
    },
    {
      "url": "http://pokeapi.co/api/v2/pokemon/467/",
      "name": "magmortar"
    },
    {
      "url": "http://pokeapi.co/api/v2/pokemon/468/",
      "name": "togekiss"
    },
    {
      "url": "http://pokeapi.co/api/v2/pokemon/469/",
      "name": "yanmega"
    },
    {
      "url": "http://pokeapi.co/api/v2/pokemon/470/",
      "name": "leafeon"
    },
    {
      "url": "http://pokeapi.co/api/v2/pokemon/471/",
      "name": "glaceon"
    },
    {
      "url": "http://pokeapi.co/api/v2/pokemon/472/",
      "name": "gliscor"
    },
    {
      "url": "http://pokeapi.co/api/v2/pokemon/473/",
      "name": "mamoswine"
    },
    {
      "url": "http://pokeapi.co/api/v2/pokemon/474/",
      "name": "porygon-z"
    },
    {
      "url": "http://pokeapi.co/api/v2/pokemon/475/",
      "name": "gallade"
    },
    {
      "url": "http://pokeapi.co/api/v2/pokemon/476/",
      "name": "probopass"
    },
    {
      "url": "http://pokeapi.co/api/v2/pokemon/477/",
      "name": "dusknoir"
    },
    {
      "url": "http://pokeapi.co/api/v2/pokemon/478/",
      "name": "froslass"
    },
    {
      "url": "http://pokeapi.co/api/v2/pokemon/479/",
      "name": "rotom"
    },
    {
      "url": "http://pokeapi.co/api/v2/pokemon/480/",
      "name": "uxie"
    },
    {
      "url": "http://pokeapi.co/api/v2/pokemon/481/",
      "name": "mesprit"
    },
    {
      "url": "http://pokeapi.co/api/v2/pokemon/482/",
      "name": "azelf"
    },
    {
      "url": "http://pokeapi.co/api/v2/pokemon/483/",
      "name": "dialga"
    },
    {
      "url": "http://pokeapi.co/api/v2/pokemon/484/",
      "name": "palkia"
    },
    {
      "url": "http://pokeapi.co/api/v2/pokemon/485/",
      "name": "heatran"
    },
    {
      "url": "http://pokeapi.co/api/v2/pokemon/486/",
      "name": "regigigas"
    },
    {
      "url": "http://pokeapi.co/api/v2/pokemon/487/",
      "name": "giratina-altered"
    },
    {
      "url": "http://pokeapi.co/api/v2/pokemon/488/",
      "name": "cresselia"
    },
    {
      "url": "http://pokeapi.co/api/v2/pokemon/489/",
      "name": "phione"
    },
    {
      "url": "http://pokeapi.co/api/v2/pokemon/490/",
      "name": "manaphy"
    },
    {
      "url": "http://pokeapi.co/api/v2/pokemon/491/",
      "name": "darkrai"
    },
    {
      "url": "http://pokeapi.co/api/v2/pokemon/492/",
      "name": "shaymin-land"
    },
    {
      "url": "http://pokeapi.co/api/v2/pokemon/493/",
      "name": "arceus"
    },
    {
      "url": "http://pokeapi.co/api/v2/pokemon/494/",
      "name": "victini"
    },
    {
      "url": "http://pokeapi.co/api/v2/pokemon/495/",
      "name": "snivy"
    },
    {
      "url": "http://pokeapi.co/api/v2/pokemon/496/",
      "name": "servine"
    },
    {
      "url": "http://pokeapi.co/api/v2/pokemon/497/",
      "name": "serperior"
    },
    {
      "url": "http://pokeapi.co/api/v2/pokemon/498/",
      "name": "tepig"
    },
    {
      "url": "http://pokeapi.co/api/v2/pokemon/499/",
      "name": "pignite"
    },
    {
      "url": "http://pokeapi.co/api/v2/pokemon/500/",
      "name": "emboar"
    },
    {
      "url": "http://pokeapi.co/api/v2/pokemon/501/",
      "name": "oshawott"
    },
    {
      "url": "http://pokeapi.co/api/v2/pokemon/502/",
      "name": "dewott"
    },
    {
      "url": "http://pokeapi.co/api/v2/pokemon/503/",
      "name": "samurott"
    },
    {
      "url": "http://pokeapi.co/api/v2/pokemon/504/",
      "name": "patrat"
    },
    {
      "url": "http://pokeapi.co/api/v2/pokemon/505/",
      "name": "watchog"
    },
    {
      "url": "http://pokeapi.co/api/v2/pokemon/506/",
      "name": "lillipup"
    },
    {
      "url": "http://pokeapi.co/api/v2/pokemon/507/",
      "name": "herdier"
    },
    {
      "url": "http://pokeapi.co/api/v2/pokemon/508/",
      "name": "stoutland"
    },
    {
      "url": "http://pokeapi.co/api/v2/pokemon/509/",
      "name": "purrloin"
    },
    {
      "url": "http://pokeapi.co/api/v2/pokemon/510/",
      "name": "liepard"
    },
    {
      "url": "http://pokeapi.co/api/v2/pokemon/511/",
      "name": "pansage"
    },
    {
      "url": "http://pokeapi.co/api/v2/pokemon/512/",
      "name": "simisage"
    },
    {
      "url": "http://pokeapi.co/api/v2/pokemon/513/",
      "name": "pansear"
    },
    {
      "url": "http://pokeapi.co/api/v2/pokemon/514/",
      "name": "simisear"
    },
    {
      "url": "http://pokeapi.co/api/v2/pokemon/515/",
      "name": "panpour"
    },
    {
      "url": "http://pokeapi.co/api/v2/pokemon/516/",
      "name": "simipour"
    },
    {
      "url": "http://pokeapi.co/api/v2/pokemon/517/",
      "name": "munna"
    },
    {
      "url": "http://pokeapi.co/api/v2/pokemon/518/",
      "name": "musharna"
    },
    {
      "url": "http://pokeapi.co/api/v2/pokemon/519/",
      "name": "pidove"
    },
    {
      "url": "http://pokeapi.co/api/v2/pokemon/520/",
      "name": "tranquill"
    },
    {
      "url": "http://pokeapi.co/api/v2/pokemon/521/",
      "name": "unfezant"
    },
    {
      "url": "http://pokeapi.co/api/v2/pokemon/522/",
      "name": "blitzle"
    },
    {
      "url": "http://pokeapi.co/api/v2/pokemon/523/",
      "name": "zebstrika"
    },
    {
      "url": "http://pokeapi.co/api/v2/pokemon/524/",
      "name": "roggenrola"
    },
    {
      "url": "http://pokeapi.co/api/v2/pokemon/525/",
      "name": "boldore"
    },
    {
      "url": "http://pokeapi.co/api/v2/pokemon/526/",
      "name": "gigalith"
    },
    {
      "url": "http://pokeapi.co/api/v2/pokemon/527/",
      "name": "woobat"
    },
    {
      "url": "http://pokeapi.co/api/v2/pokemon/528/",
      "name": "swoobat"
    },
    {
      "url": "http://pokeapi.co/api/v2/pokemon/529/",
      "name": "drilbur"
    },
    {
      "url": "http://pokeapi.co/api/v2/pokemon/530/",
      "name": "excadrill"
    },
    {
      "url": "http://pokeapi.co/api/v2/pokemon/531/",
      "name": "audino"
    },
    {
      "url": "http://pokeapi.co/api/v2/pokemon/532/",
      "name": "timburr"
    },
    {
      "url": "http://pokeapi.co/api/v2/pokemon/533/",
      "name": "gurdurr"
    },
    {
      "url": "http://pokeapi.co/api/v2/pokemon/534/",
      "name": "conkeldurr"
    },
    {
      "url": "http://pokeapi.co/api/v2/pokemon/535/",
      "name": "tympole"
    },
    {
      "url": "http://pokeapi.co/api/v2/pokemon/536/",
      "name": "palpitoad"
    },
    {
      "url": "http://pokeapi.co/api/v2/pokemon/537/",
      "name": "seismitoad"
    },
    {
      "url": "http://pokeapi.co/api/v2/pokemon/538/",
      "name": "throh"
    },
    {
      "url": "http://pokeapi.co/api/v2/pokemon/539/",
      "name": "sawk"
    },
    {
      "url": "http://pokeapi.co/api/v2/pokemon/540/",
      "name": "sewaddle"
    },
    {
      "url": "http://pokeapi.co/api/v2/pokemon/541/",
      "name": "swadloon"
    },
    {
      "url": "http://pokeapi.co/api/v2/pokemon/542/",
      "name": "leavanny"
    },
    {
      "url": "http://pokeapi.co/api/v2/pokemon/543/",
      "name": "venipede"
    },
    {
      "url": "http://pokeapi.co/api/v2/pokemon/544/",
      "name": "whirlipede"
    },
    {
      "url": "http://pokeapi.co/api/v2/pokemon/545/",
      "name": "scolipede"
    },
    {
      "url": "http://pokeapi.co/api/v2/pokemon/546/",
      "name": "cottonee"
    },
    {
      "url": "http://pokeapi.co/api/v2/pokemon/547/",
      "name": "whimsicott"
    },
    {
      "url": "http://pokeapi.co/api/v2/pokemon/548/",
      "name": "petilil"
    },
    {
      "url": "http://pokeapi.co/api/v2/pokemon/549/",
      "name": "lilligant"
    },
    {
      "url": "http://pokeapi.co/api/v2/pokemon/550/",
      "name": "basculin-red-striped"
    },
    {
      "url": "http://pokeapi.co/api/v2/pokemon/551/",
      "name": "sandile"
    },
    {
      "url": "http://pokeapi.co/api/v2/pokemon/552/",
      "name": "krokorok"
    },
    {
      "url": "http://pokeapi.co/api/v2/pokemon/553/",
      "name": "krookodile"
    },
    {
      "url": "http://pokeapi.co/api/v2/pokemon/554/",
      "name": "darumaka"
    },
    {
      "url": "http://pokeapi.co/api/v2/pokemon/555/",
      "name": "darmanitan-standard"
    },
    {
      "url": "http://pokeapi.co/api/v2/pokemon/556/",
      "name": "maractus"
    },
    {
      "url": "http://pokeapi.co/api/v2/pokemon/557/",
      "name": "dwebble"
    },
    {
      "url": "http://pokeapi.co/api/v2/pokemon/558/",
      "name": "crustle"
    },
    {
      "url": "http://pokeapi.co/api/v2/pokemon/559/",
      "name": "scraggy"
    },
    {
      "url": "http://pokeapi.co/api/v2/pokemon/560/",
      "name": "scrafty"
    },
    {
      "url": "http://pokeapi.co/api/v2/pokemon/561/",
      "name": "sigilyph"
    },
    {
      "url": "http://pokeapi.co/api/v2/pokemon/562/",
      "name": "yamask"
    },
    {
      "url": "http://pokeapi.co/api/v2/pokemon/563/",
      "name": "cofagrigus"
    },
    {
      "url": "http://pokeapi.co/api/v2/pokemon/564/",
      "name": "tirtouga"
    },
    {
      "url": "http://pokeapi.co/api/v2/pokemon/565/",
      "name": "carracosta"
    },
    {
      "url": "http://pokeapi.co/api/v2/pokemon/566/",
      "name": "archen"
    },
    {
      "url": "http://pokeapi.co/api/v2/pokemon/567/",
      "name": "archeops"
    },
    {
      "url": "http://pokeapi.co/api/v2/pokemon/568/",
      "name": "trubbish"
    },
    {
      "url": "http://pokeapi.co/api/v2/pokemon/569/",
      "name": "garbodor"
    },
    {
      "url": "http://pokeapi.co/api/v2/pokemon/570/",
      "name": "zorua"
    },
    {
      "url": "http://pokeapi.co/api/v2/pokemon/571/",
      "name": "zoroark"
    },
    {
      "url": "http://pokeapi.co/api/v2/pokemon/572/",
      "name": "minccino"
    },
    {
      "url": "http://pokeapi.co/api/v2/pokemon/573/",
      "name": "cinccino"
    },
    {
      "url": "http://pokeapi.co/api/v2/pokemon/574/",
      "name": "gothita"
    },
    {
      "url": "http://pokeapi.co/api/v2/pokemon/575/",
      "name": "gothorita"
    },
    {
      "url": "http://pokeapi.co/api/v2/pokemon/576/",
      "name": "gothitelle"
    },
    {
      "url": "http://pokeapi.co/api/v2/pokemon/577/",
      "name": "solosis"
    },
    {
      "url": "http://pokeapi.co/api/v2/pokemon/578/",
      "name": "duosion"
    },
    {
      "url": "http://pokeapi.co/api/v2/pokemon/579/",
      "name": "reuniclus"
    },
    {
      "url": "http://pokeapi.co/api/v2/pokemon/580/",
      "name": "ducklett"
    },
    {
      "url": "http://pokeapi.co/api/v2/pokemon/581/",
      "name": "swanna"
    },
    {
      "url": "http://pokeapi.co/api/v2/pokemon/582/",
      "name": "vanillite"
    },
    {
      "url": "http://pokeapi.co/api/v2/pokemon/583/",
      "name": "vanillish"
    },
    {
      "url": "http://pokeapi.co/api/v2/pokemon/584/",
      "name": "vanilluxe"
    },
    {
      "url": "http://pokeapi.co/api/v2/pokemon/585/",
      "name": "deerling"
    },
    {
      "url": "http://pokeapi.co/api/v2/pokemon/586/",
      "name": "sawsbuck"
    },
    {
      "url": "http://pokeapi.co/api/v2/pokemon/587/",
      "name": "emolga"
    },
    {
      "url": "http://pokeapi.co/api/v2/pokemon/588/",
      "name": "karrablast"
    },
    {
      "url": "http://pokeapi.co/api/v2/pokemon/589/",
      "name": "escavalier"
    },
    {
      "url": "http://pokeapi.co/api/v2/pokemon/590/",
      "name": "foongus"
    },
    {
      "url": "http://pokeapi.co/api/v2/pokemon/591/",
      "name": "amoonguss"
    },
    {
      "url": "http://pokeapi.co/api/v2/pokemon/592/",
      "name": "frillish"
    },
    {
      "url": "http://pokeapi.co/api/v2/pokemon/593/",
      "name": "jellicent"
    },
    {
      "url": "http://pokeapi.co/api/v2/pokemon/594/",
      "name": "alomomola"
    },
    {
      "url": "http://pokeapi.co/api/v2/pokemon/595/",
      "name": "joltik"
    },
    {
      "url": "http://pokeapi.co/api/v2/pokemon/596/",
      "name": "galvantula"
    },
    {
      "url": "http://pokeapi.co/api/v2/pokemon/597/",
      "name": "ferroseed"
    },
    {
      "url": "http://pokeapi.co/api/v2/pokemon/598/",
      "name": "ferrothorn"
    },
    {
      "url": "http://pokeapi.co/api/v2/pokemon/599/",
      "name": "klink"
    },
    {
      "url": "http://pokeapi.co/api/v2/pokemon/600/",
      "name": "klang"
    },
    {
      "url": "http://pokeapi.co/api/v2/pokemon/601/",
      "name": "klinklang"
    },
    {
      "url": "http://pokeapi.co/api/v2/pokemon/602/",
      "name": "tynamo"
    },
    {
      "url": "http://pokeapi.co/api/v2/pokemon/603/",
      "name": "eelektrik"
    },
    {
      "url": "http://pokeapi.co/api/v2/pokemon/604/",
      "name": "eelektross"
    },
    {
      "url": "http://pokeapi.co/api/v2/pokemon/605/",
      "name": "elgyem"
    },
    {
      "url": "http://pokeapi.co/api/v2/pokemon/606/",
      "name": "beheeyem"
    },
    {
      "url": "http://pokeapi.co/api/v2/pokemon/607/",
      "name": "litwick"
    },
    {
      "url": "http://pokeapi.co/api/v2/pokemon/608/",
      "name": "lampent"
    },
    {
      "url": "http://pokeapi.co/api/v2/pokemon/609/",
      "name": "chandelure"
    },
    {
      "url": "http://pokeapi.co/api/v2/pokemon/610/",
      "name": "axew"
    },
    {
      "url": "http://pokeapi.co/api/v2/pokemon/611/",
      "name": "fraxure"
    },
    {
      "url": "http://pokeapi.co/api/v2/pokemon/612/",
      "name": "haxorus"
    },
    {
      "url": "http://pokeapi.co/api/v2/pokemon/613/",
      "name": "cubchoo"
    },
    {
      "url": "http://pokeapi.co/api/v2/pokemon/614/",
      "name": "beartic"
    },
    {
      "url": "http://pokeapi.co/api/v2/pokemon/615/",
      "name": "cryogonal"
    },
    {
      "url": "http://pokeapi.co/api/v2/pokemon/616/",
      "name": "shelmet"
    },
    {
      "url": "http://pokeapi.co/api/v2/pokemon/617/",
      "name": "accelgor"
    },
    {
      "url": "http://pokeapi.co/api/v2/pokemon/618/",
      "name": "stunfisk"
    },
    {
      "url": "http://pokeapi.co/api/v2/pokemon/619/",
      "name": "mienfoo"
    },
    {
      "url": "http://pokeapi.co/api/v2/pokemon/620/",
      "name": "mienshao"
    },
    {
      "url": "http://pokeapi.co/api/v2/pokemon/621/",
      "name": "druddigon"
    },
    {
      "url": "http://pokeapi.co/api/v2/pokemon/622/",
      "name": "golett"
    },
    {
      "url": "http://pokeapi.co/api/v2/pokemon/623/",
      "name": "golurk"
    },
    {
      "url": "http://pokeapi.co/api/v2/pokemon/624/",
      "name": "pawniard"
    },
    {
      "url": "http://pokeapi.co/api/v2/pokemon/625/",
      "name": "bisharp"
    },
    {
      "url": "http://pokeapi.co/api/v2/pokemon/626/",
      "name": "bouffalant"
    },
    {
      "url": "http://pokeapi.co/api/v2/pokemon/627/",
      "name": "rufflet"
    },
    {
      "url": "http://pokeapi.co/api/v2/pokemon/628/",
      "name": "braviary"
    },
    {
      "url": "http://pokeapi.co/api/v2/pokemon/629/",
      "name": "vullaby"
    },
    {
      "url": "http://pokeapi.co/api/v2/pokemon/630/",
      "name": "mandibuzz"
    },
    {
      "url": "http://pokeapi.co/api/v2/pokemon/631/",
      "name": "heatmor"
    },
    {
      "url": "http://pokeapi.co/api/v2/pokemon/632/",
      "name": "durant"
    },
    {
      "url": "http://pokeapi.co/api/v2/pokemon/633/",
      "name": "deino"
    },
    {
      "url": "http://pokeapi.co/api/v2/pokemon/634/",
      "name": "zweilous"
    },
    {
      "url": "http://pokeapi.co/api/v2/pokemon/635/",
      "name": "hydreigon"
    },
    {
      "url": "http://pokeapi.co/api/v2/pokemon/636/",
      "name": "larvesta"
    },
    {
      "url": "http://pokeapi.co/api/v2/pokemon/637/",
      "name": "volcarona"
    },
    {
      "url": "http://pokeapi.co/api/v2/pokemon/638/",
      "name": "cobalion"
    },
    {
      "url": "http://pokeapi.co/api/v2/pokemon/639/",
      "name": "terrakion"
    },
    {
      "url": "http://pokeapi.co/api/v2/pokemon/640/",
      "name": "virizion"
    },
    {
      "url": "http://pokeapi.co/api/v2/pokemon/641/",
      "name": "tornadus-incarnate"
    },
    {
      "url": "http://pokeapi.co/api/v2/pokemon/642/",
      "name": "thundurus-incarnate"
    },
    {
      "url": "http://pokeapi.co/api/v2/pokemon/643/",
      "name": "reshiram"
    },
    {
      "url": "http://pokeapi.co/api/v2/pokemon/644/",
      "name": "zekrom"
    },
    {
      "url": "http://pokeapi.co/api/v2/pokemon/645/",
      "name": "landorus-incarnate"
    },
    {
      "url": "http://pokeapi.co/api/v2/pokemon/646/",
      "name": "kyurem"
    },
    {
      "url": "http://pokeapi.co/api/v2/pokemon/647/",
      "name": "keldeo-ordinary"
    },
    {
      "url": "http://pokeapi.co/api/v2/pokemon/648/",
      "name": "meloetta-aria"
    },
    {
      "url": "http://pokeapi.co/api/v2/pokemon/649/",
      "name": "genesect"
    },
    {
      "url": "http://pokeapi.co/api/v2/pokemon/650/",
      "name": "chespin"
    },
    {
      "url": "http://pokeapi.co/api/v2/pokemon/651/",
      "name": "quilladin"
    },
    {
      "url": "http://pokeapi.co/api/v2/pokemon/652/",
      "name": "chesnaught"
    },
    {
      "url": "http://pokeapi.co/api/v2/pokemon/653/",
      "name": "fennekin"
    },
    {
      "url": "http://pokeapi.co/api/v2/pokemon/654/",
      "name": "braixen"
    },
    {
      "url": "http://pokeapi.co/api/v2/pokemon/655/",
      "name": "delphox"
    },
    {
      "url": "http://pokeapi.co/api/v2/pokemon/656/",
      "name": "froakie"
    },
    {
      "url": "http://pokeapi.co/api/v2/pokemon/657/",
      "name": "frogadier"
    },
    {
      "url": "http://pokeapi.co/api/v2/pokemon/658/",
      "name": "greninja"
    },
    {
      "url": "http://pokeapi.co/api/v2/pokemon/659/",
      "name": "bunnelby"
    },
    {
      "url": "http://pokeapi.co/api/v2/pokemon/660/",
      "name": "diggersby"
    },
    {
      "url": "http://pokeapi.co/api/v2/pokemon/661/",
      "name": "fletchling"
    },
    {
      "url": "http://pokeapi.co/api/v2/pokemon/662/",
      "name": "fletchinder"
    },
    {
      "url": "http://pokeapi.co/api/v2/pokemon/663/",
      "name": "talonflame"
    },
    {
      "url": "http://pokeapi.co/api/v2/pokemon/664/",
      "name": "scatterbug"
    },
    {
      "url": "http://pokeapi.co/api/v2/pokemon/665/",
      "name": "spewpa"
    },
    {
      "url": "http://pokeapi.co/api/v2/pokemon/666/",
      "name": "vivillon"
    },
    {
      "url": "http://pokeapi.co/api/v2/pokemon/667/",
      "name": "litleo"
    },
    {
      "url": "http://pokeapi.co/api/v2/pokemon/668/",
      "name": "pyroar"
    },
    {
      "url": "http://pokeapi.co/api/v2/pokemon/669/",
      "name": "flabebe"
    },
    {
      "url": "http://pokeapi.co/api/v2/pokemon/670/",
      "name": "floette"
    },
    {
      "url": "http://pokeapi.co/api/v2/pokemon/671/",
      "name": "florges"
    },
    {
      "url": "http://pokeapi.co/api/v2/pokemon/672/",
      "name": "skiddo"
    },
    {
      "url": "http://pokeapi.co/api/v2/pokemon/673/",
      "name": "gogoat"
    },
    {
      "url": "http://pokeapi.co/api/v2/pokemon/674/",
      "name": "pancham"
    },
    {
      "url": "http://pokeapi.co/api/v2/pokemon/675/",
      "name": "pangoro"
    },
    {
      "url": "http://pokeapi.co/api/v2/pokemon/676/",
      "name": "furfrou"
    },
    {
      "url": "http://pokeapi.co/api/v2/pokemon/677/",
      "name": "espurr"
    },
    {
      "url": "http://pokeapi.co/api/v2/pokemon/678/",
      "name": "meowstic-male"
    },
    {
      "url": "http://pokeapi.co/api/v2/pokemon/679/",
      "name": "honedge"
    },
    {
      "url": "http://pokeapi.co/api/v2/pokemon/680/",
      "name": "doublade"
    },
    {
      "url": "http://pokeapi.co/api/v2/pokemon/681/",
      "name": "aegislash-shield"
    },
    {
      "url": "http://pokeapi.co/api/v2/pokemon/682/",
      "name": "spritzee"
    },
    {
      "url": "http://pokeapi.co/api/v2/pokemon/683/",
      "name": "aromatisse"
    },
    {
      "url": "http://pokeapi.co/api/v2/pokemon/684/",
      "name": "swirlix"
    },
    {
      "url": "http://pokeapi.co/api/v2/pokemon/685/",
      "name": "slurpuff"
    },
    {
      "url": "http://pokeapi.co/api/v2/pokemon/686/",
      "name": "inkay"
    },
    {
      "url": "http://pokeapi.co/api/v2/pokemon/687/",
      "name": "malamar"
    },
    {
      "url": "http://pokeapi.co/api/v2/pokemon/688/",
      "name": "binacle"
    },
    {
      "url": "http://pokeapi.co/api/v2/pokemon/689/",
      "name": "barbaracle"
    },
    {
      "url": "http://pokeapi.co/api/v2/pokemon/690/",
      "name": "skrelp"
    },
    {
      "url": "http://pokeapi.co/api/v2/pokemon/691/",
      "name": "dragalge"
    },
    {
      "url": "http://pokeapi.co/api/v2/pokemon/692/",
      "name": "clauncher"
    },
    {
      "url": "http://pokeapi.co/api/v2/pokemon/693/",
      "name": "clawitzer"
    },
    {
      "url": "http://pokeapi.co/api/v2/pokemon/694/",
      "name": "helioptile"
    },
    {
      "url": "http://pokeapi.co/api/v2/pokemon/695/",
      "name": "heliolisk"
    },
    {
      "url": "http://pokeapi.co/api/v2/pokemon/696/",
      "name": "tyrunt"
    },
    {
      "url": "http://pokeapi.co/api/v2/pokemon/697/",
      "name": "tyrantrum"
    },
    {
      "url": "http://pokeapi.co/api/v2/pokemon/698/",
      "name": "amaura"
    },
    {
      "url": "http://pokeapi.co/api/v2/pokemon/699/",
      "name": "aurorus"
    },
    {
      "url": "http://pokeapi.co/api/v2/pokemon/700/",
      "name": "sylveon"
    },
    {
      "url": "http://pokeapi.co/api/v2/pokemon/701/",
      "name": "hawlucha"
    },
    {
      "url": "http://pokeapi.co/api/v2/pokemon/702/",
      "name": "dedenne"
    },
    {
      "url": "http://pokeapi.co/api/v2/pokemon/703/",
      "name": "carbink"
    },
    {
      "url": "http://pokeapi.co/api/v2/pokemon/704/",
      "name": "goomy"
    },
    {
      "url": "http://pokeapi.co/api/v2/pokemon/705/",
      "name": "sliggoo"
    },
    {
      "url": "http://pokeapi.co/api/v2/pokemon/706/",
      "name": "goodra"
    },
    {
      "url": "http://pokeapi.co/api/v2/pokemon/707/",
      "name": "klefki"
    },
    {
      "url": "http://pokeapi.co/api/v2/pokemon/708/",
      "name": "phantump"
    },
    {
      "url": "http://pokeapi.co/api/v2/pokemon/709/",
      "name": "trevenant"
    },
    {
      "url": "http://pokeapi.co/api/v2/pokemon/710/",
      "name": "pumpkaboo-average"
    },
    {
      "url": "http://pokeapi.co/api/v2/pokemon/711/",
      "name": "gourgeist-average"
    },
    {
      "url": "http://pokeapi.co/api/v2/pokemon/712/",
      "name": "bergmite"
    },
    {
      "url": "http://pokeapi.co/api/v2/pokemon/713/",
      "name": "avalugg"
    },
    {
      "url": "http://pokeapi.co/api/v2/pokemon/714/",
      "name": "noibat"
    },
    {
      "url": "http://pokeapi.co/api/v2/pokemon/715/",
      "name": "noivern"
    },
    {
      "url": "http://pokeapi.co/api/v2/pokemon/716/",
      "name": "xerneas"
    },
    {
      "url": "http://pokeapi.co/api/v2/pokemon/717/",
      "name": "yveltal"
    },
    {
      "url": "http://pokeapi.co/api/v2/pokemon/718/",
      "name": "zygarde"
    },
    {
      "url": "http://pokeapi.co/api/v2/pokemon/719/",
      "name": "diancie"
    },
    {
      "url": "http://pokeapi.co/api/v2/pokemon/720/",
      "name": "hoopa"
    },
    {
      "url": "http://pokeapi.co/api/v2/pokemon/721/",
      "name": "volcanion"
    },
    {
      "url": "http://pokeapi.co/api/v2/pokemon/10001/",
      "name": "deoxys-attack"
    },
    {
      "url": "http://pokeapi.co/api/v2/pokemon/10002/",
      "name": "deoxys-defense"
    },
    {
      "url": "http://pokeapi.co/api/v2/pokemon/10003/",
      "name": "deoxys-speed"
    },
    {
      "url": "http://pokeapi.co/api/v2/pokemon/10004/",
      "name": "wormadam-sandy"
    },
    {
      "url": "http://pokeapi.co/api/v2/pokemon/10005/",
      "name": "wormadam-trash"
    },
    {
      "url": "http://pokeapi.co/api/v2/pokemon/10006/",
      "name": "shaymin-sky"
    },
    {
      "url": "http://pokeapi.co/api/v2/pokemon/10007/",
      "name": "giratina-origin"
    },
    {
      "url": "http://pokeapi.co/api/v2/pokemon/10008/",
      "name": "rotom-heat"
    },
    {
      "url": "http://pokeapi.co/api/v2/pokemon/10009/",
      "name": "rotom-wash"
    },
    {
      "url": "http://pokeapi.co/api/v2/pokemon/10010/",
      "name": "rotom-frost"
    },
    {
      "url": "http://pokeapi.co/api/v2/pokemon/10011/",
      "name": "rotom-fan"
    },
    {
      "url": "http://pokeapi.co/api/v2/pokemon/10012/",
      "name": "rotom-mow"
    },
    {
      "url": "http://pokeapi.co/api/v2/pokemon/10013/",
      "name": "castform-sunny"
    },
    {
      "url": "http://pokeapi.co/api/v2/pokemon/10014/",
      "name": "castform-rainy"
    },
    {
      "url": "http://pokeapi.co/api/v2/pokemon/10015/",
      "name": "castform-snowy"
    },
    {
      "url": "http://pokeapi.co/api/v2/pokemon/10016/",
      "name": "basculin-blue-striped"
    },
    {
      "url": "http://pokeapi.co/api/v2/pokemon/10017/",
      "name": "darmanitan-zen"
    },
    {
      "url": "http://pokeapi.co/api/v2/pokemon/10018/",
      "name": "meloetta-pirouette"
    },
    {
      "url": "http://pokeapi.co/api/v2/pokemon/10019/",
      "name": "tornadus-therian"
    },
    {
      "url": "http://pokeapi.co/api/v2/pokemon/10020/",
      "name": "thundurus-therian"
    },
    {
      "url": "http://pokeapi.co/api/v2/pokemon/10021/",
      "name": "landorus-therian"
    },
    {
      "url": "http://pokeapi.co/api/v2/pokemon/10022/",
      "name": "kyurem-black"
    },
    {
      "url": "http://pokeapi.co/api/v2/pokemon/10023/",
      "name": "kyurem-white"
    },
    {
      "url": "http://pokeapi.co/api/v2/pokemon/10024/",
      "name": "keldeo-resolute"
    },
    {
      "url": "http://pokeapi.co/api/v2/pokemon/10025/",
      "name": "meowstic-female"
    },
    {
      "url": "http://pokeapi.co/api/v2/pokemon/10026/",
      "name": "aegislash-blade"
    },
    {
      "url": "http://pokeapi.co/api/v2/pokemon/10027/",
      "name": "pumpkaboo-small"
    },
    {
      "url": "http://pokeapi.co/api/v2/pokemon/10028/",
      "name": "pumpkaboo-large"
    },
    {
      "url": "http://pokeapi.co/api/v2/pokemon/10029/",
      "name": "pumpkaboo-super"
    },
    {
      "url": "http://pokeapi.co/api/v2/pokemon/10030/",
      "name": "gourgeist-small"
    },
    {
      "url": "http://pokeapi.co/api/v2/pokemon/10031/",
      "name": "gourgeist-large"
    },
    {
      "url": "http://pokeapi.co/api/v2/pokemon/10032/",
      "name": "gourgeist-super"
    },
    {
      "url": "http://pokeapi.co/api/v2/pokemon/10033/",
      "name": "venusaur-mega"
    },
    {
      "url": "http://pokeapi.co/api/v2/pokemon/10034/",
      "name": "charizard-mega-x"
    },
    {
      "url": "http://pokeapi.co/api/v2/pokemon/10035/",
      "name": "charizard-mega-y"
    },
    {
      "url": "http://pokeapi.co/api/v2/pokemon/10036/",
      "name": "blastoise-mega"
    },
    {
      "url": "http://pokeapi.co/api/v2/pokemon/10037/",
      "name": "alakazam-mega"
    },
    {
      "url": "http://pokeapi.co/api/v2/pokemon/10038/",
      "name": "gengar-mega"
    },
    {
      "url": "http://pokeapi.co/api/v2/pokemon/10039/",
      "name": "kangaskhan-mega"
    },
    {
      "url": "http://pokeapi.co/api/v2/pokemon/10040/",
      "name": "pinsir-mega"
    },
    {
      "url": "http://pokeapi.co/api/v2/pokemon/10041/",
      "name": "gyarados-mega"
    },
    {
      "url": "http://pokeapi.co/api/v2/pokemon/10042/",
      "name": "aerodactyl-mega"
    },
    {
      "url": "http://pokeapi.co/api/v2/pokemon/10043/",
      "name": "mewtwo-mega-x"
    },
    {
      "url": "http://pokeapi.co/api/v2/pokemon/10044/",
      "name": "mewtwo-mega-y"
    },
    {
      "url": "http://pokeapi.co/api/v2/pokemon/10045/",
      "name": "ampharos-mega"
    },
    {
      "url": "http://pokeapi.co/api/v2/pokemon/10046/",
      "name": "scizor-mega"
    },
    {
      "url": "http://pokeapi.co/api/v2/pokemon/10047/",
      "name": "heracross-mega"
    },
    {
      "url": "http://pokeapi.co/api/v2/pokemon/10048/",
      "name": "houndoom-mega"
    },
    {
      "url": "http://pokeapi.co/api/v2/pokemon/10049/",
      "name": "tyranitar-mega"
    },
    {
      "url": "http://pokeapi.co/api/v2/pokemon/10050/",
      "name": "blaziken-mega"
    },
    {
      "url": "http://pokeapi.co/api/v2/pokemon/10051/",
      "name": "gardevoir-mega"
    },
    {
      "url": "http://pokeapi.co/api/v2/pokemon/10052/",
      "name": "mawile-mega"
    },
    {
      "url": "http://pokeapi.co/api/v2/pokemon/10053/",
      "name": "aggron-mega"
    },
    {
      "url": "http://pokeapi.co/api/v2/pokemon/10054/",
      "name": "medicham-mega"
    },
    {
      "url": "http://pokeapi.co/api/v2/pokemon/10055/",
      "name": "manectric-mega"
    },
    {
      "url": "http://pokeapi.co/api/v2/pokemon/10056/",
      "name": "banette-mega"
    },
    {
      "url": "http://pokeapi.co/api/v2/pokemon/10057/",
      "name": "absol-mega"
    },
    {
      "url": "http://pokeapi.co/api/v2/pokemon/10058/",
      "name": "garchomp-mega"
    },
    {
      "url": "http://pokeapi.co/api/v2/pokemon/10059/",
      "name": "lucario-mega"
    },
    {
      "url": "http://pokeapi.co/api/v2/pokemon/10060/",
      "name": "abomasnow-mega"
    },
    {
      "url": "http://pokeapi.co/api/v2/pokemon/10061/",
      "name": "floette-eternal"
    },
    {
      "url": "http://pokeapi.co/api/v2/pokemon/10062/",
      "name": "latias-mega"
    },
    {
      "url": "http://pokeapi.co/api/v2/pokemon/10063/",
      "name": "latios-mega"
    },
    {
      "url": "http://pokeapi.co/api/v2/pokemon/10064/",
      "name": "swampert-mega"
    },
    {
      "url": "http://pokeapi.co/api/v2/pokemon/10065/",
      "name": "sceptile-mega"
    },
    {
      "url": "http://pokeapi.co/api/v2/pokemon/10066/",
      "name": "sableye-mega"
    },
    {
      "url": "http://pokeapi.co/api/v2/pokemon/10067/",
      "name": "altaria-mega"
    },
    {
      "url": "http://pokeapi.co/api/v2/pokemon/10068/",
      "name": "gallade-mega"
    },
    {
      "url": "http://pokeapi.co/api/v2/pokemon/10069/",
      "name": "audino-mega"
    },
    {
      "url": "http://pokeapi.co/api/v2/pokemon/10070/",
      "name": "sharpedo-mega"
    },
    {
      "url": "http://pokeapi.co/api/v2/pokemon/10071/",
      "name": "slowbro-mega"
    },
    {
      "url": "http://pokeapi.co/api/v2/pokemon/10072/",
      "name": "steelix-mega"
    },
    {
      "url": "http://pokeapi.co/api/v2/pokemon/10073/",
      "name": "pidgeot-mega"
    },
    {
      "url": "http://pokeapi.co/api/v2/pokemon/10074/",
      "name": "glalie-mega"
    },
    {
      "url": "http://pokeapi.co/api/v2/pokemon/10075/",
      "name": "diancie-mega"
    },
    {
      "url": "http://pokeapi.co/api/v2/pokemon/10076/",
      "name": "metagross-mega"
    },
    {
      "url": "http://pokeapi.co/api/v2/pokemon/10077/",
      "name": "kyogre-primal"
    },
    {
      "url": "http://pokeapi.co/api/v2/pokemon/10078/",
      "name": "groudon-primal"
    },
    {
      "url": "http://pokeapi.co/api/v2/pokemon/10079/",
      "name": "rayquaza-mega"
    },
    {
      "url": "http://pokeapi.co/api/v2/pokemon/10080/",
      "name": "pikachu-rock-star"
    },
    {
      "url": "http://pokeapi.co/api/v2/pokemon/10081/",
      "name": "pikachu-belle"
    },
    {
      "url": "http://pokeapi.co/api/v2/pokemon/10082/",
      "name": "pikachu-pop-star"
    },
    {
      "url": "http://pokeapi.co/api/v2/pokemon/10083/",
      "name": "pikachu-phd"
    },
    {
      "url": "http://pokeapi.co/api/v2/pokemon/10084/",
      "name": "pikachu-libre"
    },
    {
      "url": "http://pokeapi.co/api/v2/pokemon/10085/",
      "name": "pikachu-cosplay"
    },
    {
      "url": "http://pokeapi.co/api/v2/pokemon/10086/",
      "name": "hoopa-unbound"
    },
    {
      "url": "http://pokeapi.co/api/v2/pokemon/10087/",
      "name": "camerupt-mega"
    },
    {
      "url": "http://pokeapi.co/api/v2/pokemon/10088/",
      "name": "lopunny-mega"
    },
    {
      "url": "http://pokeapi.co/api/v2/pokemon/10089/",
      "name": "salamence-mega"
    },
    {
      "url": "http://pokeapi.co/api/v2/pokemon/10090/",
      "name": "beedrill-mega"
    }
  ],
  "next": "http://pokeapi.co/api/v2/move/?offset=20"
}